a430py/__init__.py
a430py/py.typed
a430py/env/__init__.py
a430py/env/a430_gym.py
a430py/simulator/__init__.py
a430py/simulator/a430_sim.py
a430py/simulator/utils/a430_types.py
a430py/simulator/utils/acmiLogger.py
a430py/simulator/libs/liba430plane.so
a430py-0.1.3.dist-info/METADATA
a430py-0.1.3.dist-info/WHEEL
a430py-0.1.3.dist-info/licenses/LICENSE
a430py-0.1.3.dist-info/RECORD
