Metadata-Version: 2.4
Name: a430py
Version: 0.1.3
Summary: A Gymnasium environment for aircraft A430.
Author-email: Xudong Gong <gongxudong_cs@aliyun.com>
License: MIT
License-File: LICENSE
Requires-Python: >=3.12
Requires-Dist: gymnasium>=1.2.0
Requires-Dist: numpy>=2.3.2
